README.md
setup.py
mostafamatrix/__init__.py
mostafamatrix/models.py
mostafamatrix.egg-info/PKG-INFO
mostafamatrix.egg-info/SOURCES.txt
mostafamatrix.egg-info/dependency_links.txt
mostafamatrix.egg-info/top_level.txt