Metadata-Version: 2.1
Name: mostafamatrix
Version: 2.0.0
Summary: A Python library for modeling univariate time series using the Generalized Least Deviation Method (GLDM) first order.
Home-page: https://github.com/abotalebmostafa11/GLDMHO
Author: Mostafa Abotaleb
Author-email: abotalebmostafa@bk.ru
License: MIT
Project-URL: Bug Reports, https://github.com/abotalebmostafa11/GLDMHO/issues
Project-URL: Source, https://github.com/abotalebmostafa11/GLDMHO
Platform: UNKNOWN
Classifier: Programming Language :: Python :: 3.9
Classifier: Programming Language :: Python :: 3.10
Classifier: Programming Language :: Python :: 3.11
Classifier: Operating System :: OS Independent
Classifier: License :: OSI Approved :: MIT License
Classifier: Intended Audience :: Developers
Classifier: Topic :: Software Development :: Libraries :: Python Modules
Requires-Python: >=3.6
